listerature/__init__.py
listerature/module1.py
tests/__init__.py
tests/test_module1.py
listerature-0.0.0.dist-info/LICENSE.txt
listerature-0.0.0.dist-info/METADATA
listerature-0.0.0.dist-info/WHEEL
listerature-0.0.0.dist-info/top_level.txt
listerature-0.0.0.dist-info/RECORD
