Metadata-Version: 2.1
Name: listerature
Version: 0.0.0
Summary: Reading list generator
Home-page: UNKNOWN
Author: James Gregory
Author-email: james.gregory94@hotmail.co.uk
License: "MIT license"
Platform: UNKNOWN
